peridot_periscope/__init__.py
peridot_periscope/__main__.py
peridot_periscope/version/test.py
peridot_periscope-1.0.1.dist-info/entry_points.txt
peridot_periscope-1.0.1.dist-info/LICENSE.txt
peridot_periscope-1.0.1.dist-info/WHEEL
peridot_periscope-1.0.1.dist-info/METADATA
peridot_periscope-1.0.1.dist-info/RECORD
