Metadata-Version: 2.1
Name: peridot-periscope
Version: 1.0.1
Summary: Unit testing framework for the Peri.dot Programming Language
License: BSD-3-Clause
Author: Totobird
Requires-Python: >=3.8,<4.0
Classifier: License :: OSI Approved :: BSD License
Classifier: Programming Language :: Python :: 3
Classifier: Programming Language :: Python :: 3.8
Requires-Dist: peridot (>=1.1.1,<2.0.0)
